{"otherData": {},"traceEvents":[{"cat":"function","dur":197760,"name":"glfwInit","ph":"X","pid":0,"tid":1890316948,"ts":14780816008},{"cat":"function","dur":1562137,"name":"glfwCreateWindow","ph":"X","pid":0,"tid":1890316948,"ts":14781013991},{"cat":"function","dur":3779,"name":"void __cdecl Teddy::OpenGLContext::Init(void)","ph":"X","pid":0,"tid":1890316948,"ts":14782576270},{"cat":"function","dur":23,"name":"void __cdecl Teddy::WindowsWindow::SetVSync(bool)","ph":"X","pid":0,"tid":1890316948,"ts":14782580129},{"cat":"function","dur":1765045,"name":"void __cdecl Teddy::WindowsWindow::Init(const struct Teddy::WindowProps &)","ph":"X","pid":0,"tid":1890316948,"ts":14780815146},{"cat":"function","dur":1765066,"name":"__cdecl Teddy::WindowsWindow::WindowsWindow(const struct Teddy::WindowProps &)","ph":"X","pid":0,"tid":1890316948,"ts":14780815144},{"cat":"function","dur":16,"name":"void __cdecl Teddy::OpenGLRendererAPI::Init(void)","ph":"X","pid":0,"tid":1890316948,"ts":14782580256},{"cat":"function","dur":50,"name":"__cdecl Teddy::OpenGLVertexArray::OpenGLVertexArray(void)","ph":"X","pid":0,"tid":1890316948,"ts":14782580311},{"cat":"function","dur":54,"name":"__cdecl Teddy::OpenGLVertexBuffer::OpenGLVertexBuffer(unsigned int)","ph":"X","pid":0,"tid":1890316948,"ts":14782580407},{"cat":"function","dur":1,"name":"void __cdecl Teddy::OpenGLVertexBuffer::Bind(void) const","ph":"X","pid":0,"tid":1890316948,"ts":14782580514},{"cat":"function","dur":44,"name":"void __cdecl Teddy::OpenGLVertexArray::AddVertexBuffer(const class std::shared_ptr<class Teddy::VertexBuffer> &)","ph":"X","pid":0,"tid":1890316948,"ts":14782580507},{"cat":"function","dur":181,"name":"__cdecl Teddy::OpenGLIndexBuffer::OpenGLIndexBuffer(unsigned int *,unsigned int)","ph":"X","pid":0,"tid":1890316948,"ts":14782581827},{"cat":"function","dur":1,"name":"void __cdecl Teddy::OpenGLIndexBuffer::Bind(void) const","ph":"X","pid":0,"tid":1890316948,"ts":14782582102},{"cat":"function","dur":30,"name":"void __cdecl Teddy::OpenGLVertexArray::SetIndexBuffer(const class std::shared_ptr<class Teddy::IndexBuffer> &)","ph":"X","pid":0,"tid":1890316948,"ts":14782582100},{"cat":"function","dur":4,"name":"__cdecl Teddy::OpenGLVertexArray::OpenGLVertexArray(void)","ph":"X","pid":0,"tid":1890316948,"ts":14782582168},{"cat":"function","dur":2,"name":"__cdecl Teddy::OpenGLVertexBuffer::OpenGLVertexBuffer(unsigned int)","ph":"X","pid":0,"tid":1890316948,"ts":14782582204},{"cat":"function","dur":0,"name":"void __cdecl Teddy::OpenGLVertexBuffer::Bind(void) const","ph":"X","pid":0,"tid":1890316948,"ts":14782582262},{"cat":"function","dur":35,"name":"void __cdecl Teddy::OpenGLVertexArray::AddVertexBuffer(const class std::shared_ptr<class Teddy::VertexBuffer> &)","ph":"X","pid":0,"tid":1890316948,"ts":14782582261},{"cat":"function","dur":1,"name":"void __cdecl Teddy::OpenGLIndexBuffer::Bind(void) const","ph":"X","pid":0,"tid":1890316948,"ts":14782582321},{"cat":"function","dur":24,"name":"void __cdecl Teddy::OpenGLVertexArray::SetIndexBuffer(const class std::shared_ptr<class Teddy::IndexBuffer> &)","ph":"X","pid":0,"tid":1890316948,"ts":14782582321},{"cat":"function","dur":9,"name":"__cdecl Teddy::OpenGLVertexArray::OpenGLVertexArray(void)","ph":"X","pid":0,"tid":1890316948,"ts":14782583485},{"cat":"function","dur":5,"name":"__cdecl Teddy::OpenGLVertexBuffer::OpenGLVertexBuffer(unsigned int)","ph":"X","pid":0,"tid":1890316948,"ts":14782583560},{"cat":"function","dur":1,"name":"void __cdecl Teddy::OpenGLVertexBuffer::Bind(void) const","ph":"X","pid":0,"tid":1890316948,"ts":14782583612},{"cat":"function","dur":27,"name":"void __cdecl Teddy::OpenGLVertexArray::AddVertexBuffer(const class std::shared_ptr<class Teddy::VertexBuffer> &)","ph":"X","pid":0,"tid":1890316948,"ts":14782583611},{"cat":"function","dur":36,"name":"__cdecl Teddy::OpenGLTexture2D::OpenGLTexture2D(unsigned int,unsigned int)","ph":"X","pid":0,"tid":1890316948,"ts":14782584350},{"cat":"function","dur":10,"name":"void __cdecl Teddy::OpenGLTexture2D::SetData(void *,unsigned int)","ph":"X","pid":0,"tid":1890316948,"ts":14782584431},{"cat":"function","dur":338,"name":"class std::basic_string<char,struct std::char_traits<char>,class std::allocator<char> > __cdecl Teddy::OpenGLShader::ReadFile(const class std::basic_string<char,struct std::char_traits<char>,class std::allocator<char> > &)","ph":"X","pid":0,"tid":1890316948,"ts":14782584796},{"cat":"function","dur":116,"name":"class std::unordered_map<unsigned int,class std::basic_string<char,struct std::char_traits<char>,class std::allocator<char> >,struct std::hash<unsigned int>,struct std::equal_to<unsigned int>,class std::allocator<struct std::pair<unsigned int const ,class std::basic_string<char,struct std::char_traits<char>,class std::allocator<char> > > > > __cdecl Teddy::OpenGLShader::PreProcess(const class std::basic_string<char,struct std::char_traits<char>,class std::allocator<char> > &)","ph":"X","pid":0,"tid":1890316948,"ts":14782585176},{"cat":"function","dur":6378,"name":"__cdecl Teddy::OpenGLShader::OpenGLShader(const class std::basic_string<char,struct std::char_traits<char>,class std::allocator<char> > &)","ph":"X","pid":0,"tid":1890316948,"ts":14782584620},{"cat":"function","dur":251,"name":"class std::basic_string<char,struct std::char_traits<char>,class std::allocator<char> > __cdecl Teddy::OpenGLShader::ReadFile(const class std::basic_string<char,struct std::char_traits<char>,class std::allocator<char> > &)","ph":"X","pid":0,"tid":1890316948,"ts":14782591315},{"cat":"function","dur":32,"name":"class std::unordered_map<unsigned int,class std::basic_string<char,struct std::char_traits<char>,class std::allocator<char> >,struct std::hash<unsigned int>,struct std::equal_to<unsigned int>,class std::allocator<struct std::pair<unsigned int const ,class std::basic_string<char,struct std::char_traits<char>,class std::allocator<char> > > > > __cdecl Teddy::OpenGLShader::PreProcess(const class std::basic_string<char,struct std::char_traits<char>,class std::allocator<char> > &)","ph":"X","pid":0,"tid":1890316948,"ts":14782591599},{"cat":"function","dur":4513,"name":"__cdecl Teddy::OpenGLShader::OpenGLShader(const class std::basic_string<char,struct std::char_traits<char>,class std::allocator<char> > &)","ph":"X","pid":0,"tid":1890316948,"ts":14782591075},{"cat":"function","dur":133,"name":"class std::basic_string<char,struct std::char_traits<char>,class std::allocator<char> > __cdecl Teddy::OpenGLShader::ReadFile(const class std::basic_string<char,struct std::char_traits<char>,class std::allocator<char> > &)","ph":"X","pid":0,"tid":1890316948,"ts":14782595839},{"cat":"function","dur":19,"name":"class std::unordered_map<unsigned int,class std::basic_string<char,struct std::char_traits<char>,class std::allocator<char> >,struct std::hash<unsigned int>,struct std::equal_to<unsigned int>,class std::allocator<struct std::pair<unsigned int const ,class std::basic_string<char,struct std::char_traits<char>,class std::allocator<char> > > > > __cdecl Teddy::OpenGLShader::PreProcess(const class std::basic_string<char,struct std::char_traits<char>,class std::allocator<char> > &)","ph":"X","pid":0,"tid":1890316948,"ts":14782596002},{"cat":"function","dur":4590,"name":"__cdecl Teddy::OpenGLShader::OpenGLShader(const class std::basic_string<char,struct std::char_traits<char>,class std::allocator<char> > &)","ph":"X","pid":0,"tid":1890316948,"ts":14782595648},{"cat":"function","dur":20030,"name":"void __cdecl Teddy::Renderer2D::Init(void)","ph":"X","pid":0,"tid":1890316948,"ts":14782580297},{"cat":"function","dur":20102,"name":"void __cdecl Teddy::Renderer::Init(void)","ph":"X","pid":0,"tid":1890316948,"ts":14782580247},{"cat":"function","dur":1567,"name":"void __cdecl Teddy::ImGuiLayer::OnAttach(void)","ph":"X","pid":0,"tid":1890316948,"ts":14782874246},{"cat":"function","dur":1639,"name":"void __cdecl Teddy::Application::PushOverlay(class Teddy::Layer *)","ph":"X","pid":0,"tid":1890316948,"ts":14782874236},{"cat":"function","dur":2060766,"name":"__cdecl Teddy::Application::Application(const class std::basic_string<char,struct std::char_traits<char>,class std::allocator<char> > &,struct Teddy::ApplicationCommandLineArgs)","ph":"X","pid":0,"tid":1890316948,"ts":14780815127},{"cat":"function","dur":7,"name":"__cdecl Teddy::OrthographicCamera::OrthographicCamera(float,float,float,float)","ph":"X","pid":0,"tid":1890316948,"ts":14782875928},{"cat":"function","dur":514,"name":"stbi_load - OpenGLTexture2D::OpenGLTexture2D(const std:string&)","ph":"X","pid":0,"tid":1890316948,"ts":14782875972},{"cat":"function","dur":603,"name":"__cdecl Teddy::OpenGLTexture2D::OpenGLTexture2D(const class std::basic_string<char,struct std::char_traits<char>,class std::allocator<char> > &)","ph":"X","pid":0,"tid":1890316948,"ts":14782875969},{"cat":"function","dur":1028,"name":"stbi_load - OpenGLTexture2D::OpenGLTexture2D(const std:string&)","ph":"X","pid":0,"tid":1890316948,"ts":14782876598},{"cat":"function","dur":1128,"name":"__cdecl Teddy::OpenGLTexture2D::OpenGLTexture2D(const class std::basic_string<char,struct std::char_traits<char>,class std::allocator<char> > &)","ph":"X","pid":0,"tid":1890316948,"ts":14782876597},{"cat":"function","dur":132,"name":"stbi_load - OpenGLTexture2D::OpenGLTexture2D(const std:string&)","ph":"X","pid":0,"tid":1890316948,"ts":14782877883},{"cat":"function","dur":174,"name":"__cdecl Teddy::OpenGLTexture2D::OpenGLTexture2D(const class std::basic_string<char,struct std::char_traits<char>,class std::allocator<char> > &)","ph":"X","pid":0,"tid":1890316948,"ts":14782877883},{"cat":"function","dur":327,"name":"stbi_load - OpenGLTexture2D::OpenGLTexture2D(const std:string&)","ph":"X","pid":0,"tid":1890316948,"ts":14782878088},{"cat":"function","dur":386,"name":"__cdecl Teddy::OpenGLTexture2D::OpenGLTexture2D(const class std::basic_string<char,struct std::char_traits<char>,class std::allocator<char> > &)","ph":"X","pid":0,"tid":1890316948,"ts":14782878087},{"cat":"function","dur":305,"name":"stbi_load - OpenGLTexture2D::OpenGLTexture2D(const std:string&)","ph":"X","pid":0,"tid":1890316948,"ts":14782878505},{"cat":"function","dur":345,"name":"__cdecl Teddy::OpenGLTexture2D::OpenGLTexture2D(const class std::basic_string<char,struct std::char_traits<char>,class std::allocator<char> > &)","ph":"X","pid":0,"tid":1890316948,"ts":14782878504},{"cat":"function","dur":5864,"name":"void __cdecl Teddy::EditorLayer::OnAttach(void)","ph":"X","pid":0,"tid":1890316948,"ts":14782877754},{"cat":"function","dur":5935,"name":"void __cdecl Teddy::Application::PushLayer(class Teddy::Layer *)","ph":"X","pid":0,"tid":1890316948,"ts":14782877748}]}